{
  "version": "7",
  "dialect": "mysql",
  "entries": [
    {
      "idx": 0,
      "version": "5",
      "when": 1768706765452,
      "tag": "0000_motionless_mockingbird",
      "breakpoints": true
    },
    {
      "idx": 1,
      "version": "5",
      "when": 1768706878365,
      "tag": "0001_flawless_galactus",
      "breakpoints": true
    },
    {
      "idx": 2,
      "version": "5",
      "when": 1768783826198,
      "tag": "0002_brown_black_tom",
      "breakpoints": true
    },
    {
      "idx": 3,
      "version": "5",
      "when": 1768784500172,
      "tag": "0003_smiling_mongu",
      "breakpoints": true
    }
  ]
}